{
  "version": "2026-05-19",
  "generated_at": "2026-05-19T06:44:11Z",
  "content": {
    "shower": [
      {
        "id": "gen_shower_20260519_001",
        "thought": "We spend the first part of life learning to be ourselves, and the second part unlearning what we learned.",
        "type": "shower",
        "source": "generated"
      },
      {
        "id": "gen_shower_20260519_002",
        "thought": "If you've never been bored, you've never really thought about anything.",
        "type": "shower",
        "source": "generated"
      },
      {
        "id": "gen_shower_20260519_003",
        "thought": "The only time you're truly present is when you've forgotten to check the time.",
        "type": "shower",
        "source": "generated"
      },
      {
        "id": "gen_shower_20260519_004",
        "thought": "You can't prove you're conscious, which means you can't prove anyone else isn't.",
        "type": "shower",
        "source": "generated"
      },
      {
        "id": "gen_shower_20260519_005",
        "thought": "Nostalgia is just homesickness for a time you can never actually return to, no matter how hard you try.",
        "type": "shower",
        "source": "generated"
      },
      {
        "id": "gen_shower_20260519_006",
        "thought": "We call it \"falling in love\" because there's no net to catch you if it goes wrong.",
        "type": "shower",
        "source": "generated"
      },
      {
        "id": "gen_shower_20260519_007",
        "thought": "Every conversation you have with a stranger is a story they'll never fully tell anyone else.",
        "type": "shower",
        "source": "generated"
      },
      {
        "id": "gen_shower_20260519_008",
        "thought": "The best teachers are usually the ones who remember being confused.",
        "type": "shower",
        "source": "generated"
      },
      {
        "id": "gen_shower_20260519_009",
        "thought": "You only know what food tastes like by comparing it to other food you've eaten, so your first meal was your only pure experience of taste.",
        "type": "shower",
        "source": "generated"
      },
      {
        "id": "gen_shower_20260519_010",
        "thought": "Money is just a collective agreement to value something invisible.",
        "type": "shower",
        "source": "generated"
      },
      {
        "id": "gen_shower_20260519_011",
        "thought": "The things you're most afraid of saying are probably the things someone else is desperate to hear.",
        "type": "shower",
        "source": "generated"
      },
      {
        "id": "gen_shower_20260519_012",
        "thought": "You've probably had the same thought as millions of people, but never at the same exact moment, which makes you lonelier than you think.",
        "type": "shower",
        "source": "generated"
      },
      {
        "id": "gen_shower_20260519_013",
        "thought": "Success often feels empty because you spent so long chasing it that you forgot why you started.",
        "type": "shower",
        "source": "generated"
      },
      {
        "id": "gen_shower_20260519_014",
        "thought": "The older you get, the faster time moves, which means life actually accelerates toward its end.",
        "type": "shower",
        "source": "generated"
      },
      {
        "id": "gen_shower_20260519_015",
        "thought": "A person with nothing to lose is the most dangerous and most free person in the room.",
        "type": "shower",
        "source": "generated"
      },
      {
        "id": "gen_shower_20260519_016",
        "thought": "You can't remember most of your life, which means you're already a ghost of who you used to be.",
        "type": "shower",
        "source": "generated"
      },
      {
        "id": "gen_shower_20260519_017",
        "thought": "The world makes sense until you ask why, and then it falls apart.",
        "type": "shower",
        "source": "generated"
      },
      {
        "id": "gen_shower_20260519_018",
        "thought": "We fear the unknown, but the known is just the unknown we've gotten used to.",
        "type": "shower",
        "source": "generated"
      },
      {
        "id": "gen_shower_20260519_019",
        "thought": "Forgiveness isn't about the other person—it's about releasing the person they made you become.",
        "type": "shower",
        "source": "generated"
      },
      {
        "id": "gen_shower_20260519_020",
        "thought": "Your biggest fear and your greatest strength are often the same thing.",
        "type": "shower",
        "source": "generated"
      }
    ],
    "motivational": [
      {
        "id": "gen_motiv_20260519_001",
        "thought": "Your potential is not something you find. It's something you build. — Unknown",
        "type": "motivational",
        "source": "generated"
      },
      {
        "id": "gen_motiv_20260519_002",
        "thought": "The best time to plant a tree was 20 years ago. The second best time is now. — Ancient Proverb",
        "type": "motivational",
        "source": "generated"
      },
      {
        "id": "gen_motiv_20260519_003",
        "thought": "Comfort is the enemy of growth. Choose the harder path. — Unknown",
        "type": "motivational",
        "source": "generated"
      },
      {
        "id": "gen_motiv_20260519_004",
        "thought": "You're not behind. You're not ahead. You're exactly where you need to be to learn what comes next. — Unknown",
        "type": "motivational",
        "source": "generated"
      },
      {
        "id": "gen_motiv_20260519_005",
        "thought": "Discipline is choosing what you want most over what you want now. — Unknown",
        "type": "motivational",
        "source": "generated"
      },
      {
        "id": "gen_motiv_20260519_006",
        "thought": "The person you'll be in five years is determined by the books you read and the people you surround yourself with today. — Unknown",
        "type": "motivational",
        "source": "generated"
      },
      {
        "id": "gen_motiv_20260519_007",
        "thought": "Comparison is the thief of contentment and the killer of ambition. Pick one and commit. — Unknown",
        "type": "motivational",
        "source": "generated"
      },
      {
        "id": "gen_motiv_20260519_008",
        "thought": "Your past doesn't define you. Your next decision does. — Unknown",
        "type": "motivational",
        "source": "generated"
      },
      {
        "id": "gen_motiv_20260519_009",
        "thought": "The only real failure is the failure to try. Everything else is just data. — Unknown",
        "type": "motivational",
        "source": "generated"
      },
      {
        "id": "gen_motiv_20260519_010",
        "thought": "Start before you're ready. Readiness is a myth we tell ourselves to avoid the work. — Unknown",
        "type": "motivational",
        "source": "generated"
      },
      {
        "id": "gen_motiv_20260519_011",
        "thought": "What lies behind you and what lies before you pale in comparison to what lies within you. — Ralph Waldo Emerson",
        "type": "motivational",
        "source": "generated"
      },
      {
        "id": "gen_motiv_20260519_012",
        "thought": "Every scar is proof you survived something that tried to break you. Wear it. — Unknown",
        "type": "motivational",
        "source": "generated"
      },
      {
        "id": "gen_motiv_20260519_013",
        "thought": "The world doesn't need another person who knows what to do. It needs someone willing to actually do it. — Unknown",
        "type": "motivational",
        "source": "generated"
      },
      {
        "id": "gen_motiv_20260519_014",
        "thought": "You don't rise to the level of your goals. You fall to the level of your systems. — Unknown",
        "type": "motivational",
        "source": "generated"
      },
      {
        "id": "gen_motiv_20260519_015",
        "thought": "Small progress is still progress. A river carves a canyon one drop at a time. — Unknown",
        "type": "motivational",
        "source": "generated"
      },
      {
        "id": "gen_motiv_20260519_016",
        "thought": "The only permission you need is your own. Stop waiting for someone else to believe in you first. — Unknown",
        "type": "motivational",
        "source": "generated"
      },
      {
        "id": "gen_motiv_20260519_017",
        "thought": "You can spend your life climbing the ladder only to realize it's leaning against the wrong wall. Choose your wall carefully. — Unknown",
        "type": "motivational",
        "source": "generated"
      },
      {
        "id": "gen_motiv_20260519_018",
        "thought": "Excellence is not a destination. It's a direction. — Unknown",
        "type": "motivational",
        "source": "generated"
      },
      {
        "id": "gen_motiv_20260519_019",
        "thought": "Your future self is watching you right now, waiting to see if you're going to do what it takes. — Unknown",
        "type": "motivational",
        "source": "generated"
      },
      {
        "id": "gen_motiv_20260519_020",
        "thought": "The gap between who you are and who you want to be is filled with the work you're willing to do. — Unknown",
        "type": "motivational",
        "source": "generated"
      }
    ],
    "darkjoke": [
      {
        "id": "gen_dark_20260519_001",
        "thought": "I told my therapist I was afraid of commitment.\nShe said, \"Let's book you for the same time next week,\" and suddenly I was terrified.",
        "type": "darkjoke",
        "source": "generated"
      },
      {
        "id": "gen_dark_20260519_002",
        "thought": "My friend asked if I believed in ghosts.\nI said, \"Not until the credit card bill for my ex's funeral showed up.\"",
        "type": "darkjoke",
        "source": "generated"
      },
      {
        "id": "gen_dark_20260519_003",
        "thought": "I went to a self-help seminar on confidence.\nThe speaker said, \"Act like you belong anywhere.\" I'm now banned from three country clubs and a courthouse.",
        "type": "darkjoke",
        "source": "generated"
      },
      {
        "id": "gen_dark_20260519_004",
        "thought": "My dad asked why I wasn't married yet.\nI said, \"I'm waiting for the right person.\" He said, \"At this rate, you'll be waiting for someone who's already married to someone else.\"",
        "type": "darkjoke",
        "source": "generated"
      },
      {
        "id": "gen_dark_20260519_005",
        "thought": "I told my friend he had unrealistic expectations about life.\nHe said, \"Says the guy who still thinks his parents are proud of him.\"",
        "type": "darkjoke",
        "source": "generated"
      },
      {
        "id": "gen_dark_20260519_006",
        "thought": "My doctor told me I was overweight.\nI said, \"Second opinion?\" He said, \"You're also ugly.\"",
        "type": "darkjoke",
        "source": "generated"
      },
      {
        "id": "gen_dark_20260519_007",
        "thought": "I asked my boss if I could work from home.\nHe said, \"Sure, as soon as you prove you can work from the office.\"",
        "type": "darkjoke",
        "source": "generated"
      },
      {
        "id": "gen_dark_20260519_008",
        "thought": "My therapist asked about my childhood.\nI said, \"It was fine.\" She said, \"That explains so much.\"",
        "type": "darkjoke",
        "source": "generated"
      },
      {
        "id": "gen_dark_20260519_009",
        "thought": "I tried to join a gym.\nThe trainer said, \"First, tell me your fitness goals.\" I said, \"To not be here.\" He said, \"Then you're already succeeding.\"",
        "type": "darkjoke",
        "source": "generated"
      },
      {
        "id": "gen_dark_20260519_010",
        "thought": "My friend said he was \"living his best life.\"\nI asked where. He said, \"In his imagination.\" I said, \"That's the saddest part—he's still unhappy there.\"",
        "type": "darkjoke",
        "source": "generated"
      },
      {
        "id": "gen_dark_20260519_011",
        "thought": "I told my mom I was becoming a minimalist.\nShe said, \"That's just what poor people call it.\"",
        "type": "darkjoke",
        "source": "generated"
      },
      {
        "id": "gen_dark_20260519_012",
        "thought": "My coworker asked if I was okay.\nI said, \"Yeah, why?\" He said, \"You've been staring at your spreadsheet for an hour without moving.\" I said, \"It's either meditation or a cry for help.\" He said, \"It's showing.\"",
        "type": "darkjoke",
        "source": "generated"
      },
      {
        "id": "gen_dark_20260519_013",
        "thought": "I asked my friend if he had any regrets.\nHe said, \"Just one.\" I said, \"What?\" He said, \"Having this conversation with you.\"",
        "type": "darkjoke",
        "source": "generated"
      },
      {
        "id": "gen_dark_20260519_014",
        "thought": "My therapist asked if I was suicidal.\nI said, \"Only on weekdays.\" She said, \"That's progress. Last week it was weekdays and weekends.\"",
        "type": "darkjoke",
        "source": "generated"
      },
      {
        "id": "gen_dark_20260519_015",
        "thought": "I told my date I had a five-year plan.\nShe asked what it was. I said, \"Make it to six years.\" She said, \"That's the most honest thing anyone's said to me, and I hate it.\"",
        "type": "darkjoke",
        "source": "generated"
      },
      {
        "id": "gen_dark_20260519_016",
        "thought": "My friend said, \"I think I'm depressed.\"\nI said, \"Have you tried being happy?\" He said, \"That's not how it works.\" I said, \"I know—I've been trying for years.\"",
        "type": "darkjoke",
        "source": "generated"
      },
      {
        "id": "gen_dark_20260519_017",
        "thought": "I asked my barber how he stays positive.\nHe said, \"I don't—I just cut hair and judge people quietly.\" Finally, someone being honest.",
        "type": "darkjoke",
        "source": "generated"
      },
      {
        "id": "gen_dark_20260519_018",
        "thought": "My mom asked if I was seeing anyone.\nI said, \"Just my therapist and my creditors. Them I see constantly.\"",
        "type": "darkjoke",
        "source": "generated"
      },
      {
        "id": "gen_dark_20260519_019",
        "thought": "I told my friend he should be more optimistic.\nHe said, \"Easy for you to say.\" I said, \"What do you mean?\" He said, \"You're delusional—that's basically the same thing.\"",
        "type": "darkjoke",
        "source": "generated"
      },
      {
        "id": "gen_dark_20260519_020",
        "thought": "My doctor said I needed to exercise more.\nI said, \"I walk to my car.\" He said, \"That's a start.\" I said, \"From the couch.\"",
        "type": "darkjoke",
        "source": "generated"
      }
    ]
  }
}